test.py
asyncgauth/__init__.py
asyncgauth/constants.py
asyncgauth/default.py
asyncgauth/exceptions.py
asyncgauth/metadata_server_auth.py
asyncgauth/oauth.py
asyncgauth/types.py
asyncgauth-0.1.1.dist-info/LICENSE
asyncgauth-0.1.1.dist-info/METADATA
asyncgauth-0.1.1.dist-info/WHEEL
asyncgauth-0.1.1.dist-info/top_level.txt
asyncgauth-0.1.1.dist-info/RECORD
