Metadata-Version: 2.1
Name: asyncgauth
Version: 0.1.1
Summary: Async Google Auth
Author-email: Hong Shick Pak <hong@hspak.com>
Project-URL: Homepage, https://github.com/hspak/asyncgauth
Project-URL: Issues, https://github.com/pypa/asyncgauth/issues
Classifier: Programming Language :: Python :: 3
Classifier: License :: OSI Approved :: MIT License
Classifier: Operating System :: OS Independent
Requires-Python: >=3.11
License-File: LICENSE
Requires-Dist: httpx
Requires-Dist: pydantic
